pycities/__init__.py
pycities/config.py
pycities/database.py
pycities/datadownload.py
pycities/datadump.py
pycities/model.py
pycities/utils.py
pycities/data/data.db
pycities-0.2.0.dist-info/LICENSE
pycities-0.2.0.dist-info/METADATA
pycities-0.2.0.dist-info/WHEEL
pycities-0.2.0.dist-info/top_level.txt
pycities-0.2.0.dist-info/RECORD
